bible_parser/__init__.py
bible_parser/bible_parser.py
bible_parser/bible_repository.py
bible_parser/errors.py
bible_parser/models.py
bible_parser/reference_formatter.py
bible_parser/parsers/__init__.py
bible_parser/parsers/base_parser.py
bible_parser/parsers/osis_parser.py
bible_parser/parsers/usfx_parser.py
bible_parser/parsers/zefania_parser.py
bible_xml_parser-0.2.1.dist-info/licenses/LICENSE
bible_xml_parser-0.2.1.dist-info/METADATA
bible_xml_parser-0.2.1.dist-info/WHEEL
bible_xml_parser-0.2.1.dist-info/top_level.txt
bible_xml_parser-0.2.1.dist-info/RECORD
