Metadata-Version: 2.4
Name: bible-xml-parser
Version: 0.2.1
Summary: A Python package for parsing Bible texts in various XML formats (USFX, OSIS, ZEFANIA) with Bible reference parsing
Author: Omar Zintan
License-Expression: MIT
Project-URL: Homepage, https://github.com/Omarzintan/bible_parser_python
Project-URL: Repository, https://github.com/Omarzintan/bible_parser_python
Project-URL: Issues, https://github.com/Omarzintan/bible_parser_python/issues
Keywords: bible,parser,xml,usfx,osis,zefania,scripture
Classifier: Development Status :: 4 - Beta
Classifier: Intended Audience :: Developers
Classifier: Programming Language :: Python :: 3
Classifier: Programming Language :: Python :: 3.8
Classifier: Programming Language :: Python :: 3.9
Classifier: Programming Language :: Python :: 3.10
Classifier: Programming Language :: Python :: 3.11
Classifier: Programming Language :: Python :: 3.12
Classifier: Topic :: Religion
Classifier: Topic :: Text Processing :: Markup :: XML
Requires-Python: >=3.8
License-File: LICENSE
Requires-Dist: defusedxml>=0.7.1
Requires-Dist: typing-extensions>=4.0.0; python_version < "3.9"
Provides-Extra: dev
Requires-Dist: pytest>=7.0.0; extra == "dev"
Requires-Dist: pytest-cov>=4.0.0; extra == "dev"
Requires-Dist: black>=23.0.0; extra == "dev"
Requires-Dist: mypy>=1.0.0; extra == "dev"
Requires-Dist: ruff>=0.1.0; extra == "dev"
Dynamic: license-file
